playwhe/__init__.py
playwhe/__main__.py
playwhe/common.py
playwhe/constants.py
playwhe/errors.py
playwhe/cli/__init__.py
playwhe/cli/schema.py
playwhe/cli/store.py
playwhe/client/__init__.py
playwhe/client/fetcher.py
playwhe/client/parser.py
playwhe-0.8.0a2.dist-info/LICENSE.txt
playwhe-0.8.0a2.dist-info/METADATA
playwhe-0.8.0a2.dist-info/WHEEL
playwhe-0.8.0a2.dist-info/entry_points.txt
playwhe-0.8.0a2.dist-info/top_level.txt
playwhe-0.8.0a2.dist-info/RECORD
