Metadata-Version: 2.1
Name: playwhe
Version: 0.8.0a2
Summary: A Python library and CLI for fetching and storing Play Whe results.
Home-page: https://github.com/playwhesmarter/playwhe
Author: Dwayne Crooks
Author-email: me@dwaynecrooks.com
License: MIT
Keywords: nlcb,playwhe
Platform: UNKNOWN
Classifier: Development Status :: 3 - Alpha
Classifier: Environment :: Console
Classifier: Intended Audience :: Developers
Classifier: Intended Audience :: End Users/Desktop
Classifier: License :: OSI Approved :: MIT License
Classifier: Operating System :: POSIX :: Linux
Classifier: Programming Language :: Python
Classifier: Programming Language :: Python :: 3.7
Classifier: Programming Language :: Python :: Implementation :: CPython
Requires-Dist: requests
Requires-Dist: sqlalchemy
